{"accept": 0, "accident": 1, "act": 2, "action": 3, "activity": 4, "actor": 5, "actres": 6, "acura": 7, "addiction": 8, "addres": 9, "adjust": 10, "admire": 11, "adult": 12, "adventure": 13, "advertise": 14, "advertisement": 15, "advertising": 16, "aeroplane": 17, "africa": 18, "aim": 19, "air": 20, "airplane": 21, "airport": 22, "aisle": 23, "alien": 24, "alligator": 25, "alpaca": 26, "amaze": 27, "ambulance": 28, "america": 29, "analyst": 30, "anchor": 31, "animal": 32, "animation": 33, "anime": 34, "announce": 35, "announcement": 36, "announcer": 37, "annoy": 38, "answer": 39, "antelope": 40, "app": 41, "applaud": 42, "apple": 43, "application": 44, "approach": 45, "aquarium": 46, "area": 47, "arena": 48, "argue": 49, "argument": 50, "arm": 51, "army": 52, "arrange": 53, "arrow": 54, "art": 55, "article": 56, "artist": 57, "ask": 58, "athlete": 59, "attach": 60, "attack": 61, "attempt": 62, "attend": 63, "audi": 64, "audience": 65, "audition": 66, "auditorium": 67, "auto": 68, "autograph": 69, "automobile": 70, "avoid": 71, "award": 72, "baby": 73, "back": 74, "backflip": 75, "background": 76, "backpack": 77, "backyard": 78, "badminton": 79, "bag": 80, "bake": 81, "balance": 82, "bald": 83, "ball": 84, "ballet": 85, "banana": 86, "band": 87, "bar": 88, "barack": 89, "barbie": 90, "bark": 91, "bartender": 92, "base": 93, "baseball": 94, "basket": 95, "basketball": 96, "bat": 97, "bath": 98, "bathroom": 99, "bathtub": 100, "batman": 101, "batter": 102, "battle": 103, "battlefield": 104, "bbc": 105, "beach": 106, "bean": 107, "bear": 108, "beat": 109, "beautiful": 110, "beauty": 111, "become": 112, "bed": 113, "bedroom": 114, "beef": 115, "beer": 116, "begin": 117, "bench": 118, "beside": 119, "bicycle": 120, "bike": 121, "biker": 122, "bikini": 123, "bill": 124, "bird": 125, "birth": 126, "birthday": 127, "blend": 128, "blender": 129, "blink": 130, "block": 131, "blond": 132, "blonde": 133, "blow": 134, "blue": 135, "board": 136, "boat": 137, "body": 138, "boil": 139, "bollywood": 140, "bomb": 141, "book": 142, "bottle": 143, "bounce": 144, "bow": 145, "bowl": 146, "box": 147, "boxer": 148, "boxing": 149, "boy": 150, "boyfriend": 151, "bra": 152, "brad": 153, "brain": 154, "brake": 155, "branch": 156, "bread": 157, "break": 158, "breakfast": 159, "bride": 160, "bridge": 161, "bring": 162, "britney": 163, "brittany": 164, "broadcast": 165, "brown": 166, "browse": 167, "brunette": 168, "brush": 169, "bucket": 170, "bug": 171, "build": 172, "building": 173, "bull": 174, "burger": 175, "burn": 176, "busines": 177, "butter": 178, "butterfly": 179, "button": 180, "cage": 181, "cake": 182, "call": 183, "camel": 184, "camera": 185, "campaign": 186, "candidate": 187, "candle": 188, "candy": 189, "cap": 190, "captain": 191, "capture": 192, "car": 193, "card": 194, "care": 195, "career": 196, "carpenter": 197, "carpet": 198, "carriage": 199, "carrot": 200, "carry": 201, "cart": 202, "cartoon": 203, "carve": 204, "case": 205, "cast": 206, "castle": 207, "cat": 208, "catch": 209, "catwalk": 210, "cause": 211, "cave": 212, "ceiling": 213, "celebrate": 214, "celebration": 215, "celebrity": 216, "cell": 217, "cellphone": 218, "center": 219, "cereal": 220, "ceremony": 221, "chair": 222, "challenge": 223, "change": 224, "channel": 225, "chant": 226, "character": 227, "chart": 228, "chase": 229, "chat": 230, "check": 231, "cheek": 232, "cheer": 233, "cheese": 234, "cheetah": 235, "chef": 236, "ches": 237, "chicago": 238, "chicken": 239, "child": 240, "china": 241, "chocolate": 242, "choice": 243, "choir": 244, "chop": 245, "christma": 246, "church": 247, "cigarette": 248, "circle": 249, "city": 250, "clap": 251, "clas": 252, "classroom": 253, "clay": 254, "clean": 255, "cliff": 256, "climb": 257, "clinton": 258, "clip": 259, "cloth": 260, "clothing": 261, "club": 262, "cnn": 263, "coach": 264, "coat": 265, "coffee": 266, "coin": 267, "collect": 268, "college": 269, "color": 270, "comb": 271, "combat": 272, "comedian": 273, "comedy": 274, "comment": 275, "commentary": 276, "commentate": 277, "commentator": 278, "communicate": 279, "company": 280, "compare": 281, "compete": 282, "competition": 283, "compilation": 284, "complain": 285, "computer": 286, "conan": 287, "concept": 288, "concert": 289, "condom": 290, "conduct": 291, "conference": 292, "confront": 293, "congratulate": 294, "consist": 295, "console": 296, "construction": 297, "contain": 298, "container": 299, "content": 300, "contest": 301, "contestant": 302, "control": 303, "convention": 304, "conversation": 305, "converse": 306, "cook": 307, "cookie": 308, "cooking": 309, "cool": 310, "corner": 311, "cort": 312, "costume": 313, "couch": 314, "count": 315, "countdown": 316, "counter": 317, "country": 318, "couple": 319, "course": 320, "court": 321, "cover": 322, "coversation": 323, "cow": 324, "cowboy": 325, "crab": 326, "crack": 327, "craft": 328, "crash": 329, "crawl": 330, "cream": 331, "create": 332, "creature": 333, "cricket": 334, "crocodile": 335, "cros": 336, "crowd": 337, "crown": 338, "crush": 339, "cruz": 340, "cry": 341, "cube": 342, "cuddle": 343, "cup": 344, "curse": 345, "customer": 346, "cut": 347, "cute": 348, "cycle": 349, "dad": 350, "damon": 351, "dance": 352, "dancing": 353, "dark": 354, "dash": 355, "dashboard": 356, "date": 357, "daughter": 358, "david": 359, "day": 360, "death": 361, "debate": 362, "decorate": 363, "deer": 364, "deliver": 365, "demo": 366, "demonstrate": 367, "demonstration": 368, "dentist": 369, "depict": 370, "describe": 371, "desert": 372, "design": 373, "designer": 374, "desk": 375, "desktop": 376, "dessert": 377, "destroy": 378, "destruction": 379, "detail": 380, "device": 381, "diagram": 382, "die": 383, "dig": 384, "din": 385, "dinner": 386, "dinosaur": 387, "dip": 388, "director": 389, "dirt": 390, "discus": 391, "discussion": 392, "dish": 393, "disney": 394, "display": 395, "distance": 396, "dive": 397, "dock": 398, "doctor": 399, "documentary": 400, "dog": 401, "doll": 402, "dolphin": 403, "donald": 404, "donkey": 405, "door": 406, "doorway": 407, "dough": 408, "drag": 409, "dragon": 410, "drain": 411, "drama": 412, "draw": 413, "drawing": 414, "dres": 415, "drift": 416, "drink": 417, "drinking": 418, "drip": 419, "drive": 420, "driver": 421, "driveway": 422, "driving": 423, "drop": 424, "drummer": 425, "dry": 426, "duck": 427, "duet": 428, "dummy": 429, "dunk": 430, "eachother": 431, "eagle": 432, "earth": 433, "eat": 434, "edit": 435, "education": 436, "egg": 437, "egypt": 438, "election": 439, "electricity": 440, "elephant": 441, "elevator": 442, "ellen": 443, "embrace": 444, "end": 445, "enemy": 446, "energy": 447, "engage": 448, "engine": 449, "engineering": 450, "enjoy": 451, "enter": 452, "entertain": 453, "entertainment": 454, "environment": 455, "equipment": 456, "escape": 457, "event": 458, "everyone": 459, "examine": 460, "exercise": 461, "exit": 462, "experience": 463, "experiment": 464, "expert": 465, "explain": 466, "explanation": 467, "explode": 468, "explore": 469, "explosion": 470, "expres": 471, "eye": 472, "eyeliner": 473, "fabric": 474, "face": 475, "factory": 476, "fall": 477, "fallon": 478, "family": 479, "fan": 480, "farm": 481, "farmer": 482, "fashion": 483, "fatality": 484, "father": 485, "fear": 486, "feature": 487, "feed": 488, "feel": 489, "female": 490, "fence": 491, "ferrarus": 492, "festival": 493, "field": 494, "fight": 495, "fighter": 496, "fighting": 497, "figure": 498, "fill": 499, "film": 500, "finger": 501, "finish": 502, "fire": 503, "firework": 504, "fish": 505, "fishing": 506, "fit": 507, "five": 508, "fix": 509, "flag": 510, "flame": 511, "flash": 512, "flight": 513, "flip": 514, "flmy": 515, "float": 516, "flood": 517, "floor": 518, "flooring": 519, "flow": 520, "flower": 521, "fly": 522, "focu": 523, "fold": 524, "folding": 525, "food": 526, "foot": 527, "footage": 528, "football": 529, "forest": 530, "fork": 531, "form": 532, "foul": 533, "four": 534, "fox": 535, "frame": 536, "freddie": 537, "freddy": 538, "fridge": 539, "friend": 540, "frog": 541, "front": 542, "fruit": 543, "fry": 544, "frying": 545, "fun": 546, "function": 547, "future": 548, "game": 549, "gameplay": 550, "gamer": 551, "garage": 552, "garden": 553, "garlic": 554, "gate": 555, "gather": 556, "gear": 557, "gentleman": 558, "george": 559, "germany": 560, "gesture": 561, "ghost": 562, "gift": 563, "ginger": 564, "girl": 565, "glas": 566, "glitter": 567, "globe": 568, "glow": 569, "glue": 570, "goal": 571, "god": 572, "gold": 573, "golf": 574, "golfer": 575, "google": 576, "gordon": 577, "grab": 578, "grain": 579, "graph": 580, "gras": 581, "gravy": 582, "graze": 583, "green": 584, "greet": 585, "grill": 586, "grind": 587, "groom": 588, "ground": 589, "group": 590, "grow": 591, "guest": 592, "guitar": 593, "guitarist": 594, "gun": 595, "guy": 596, "gym": 597, "gymnasium": 598, "gymnast": 599, "hair": 600, "haircut": 601, "half": 602, "hall": 603, "hallway": 604, "hammer": 605, "hamster": 606, "hand": 607, "handle": 608, "hang": 609, "harvey": 610, "hat": 611, "head": 612, "health": 613, "hear": 614, "heart": 615, "heat": 616, "helicopter": 617, "helmet": 618, "help": 619, "herb": 620, "hero": 621, "herself": 622, "hide": 623, "highlight": 624, "highway": 625, "hike": 626, "hill": 627, "hillary": 628, "hip": 629, "history": 630, "hit": 631, "hockey": 632, "hold": 633, "hole": 634, "hollywood": 635, "home": 636, "honda": 637, "honey": 638, "hood": 639, "hoop": 640, "hop": 641, "horizon": 642, "horror": 643, "horse": 644, "hospital": 645, "host": 646, "hotel": 647, "house": 648, "hug": 649, "hulk": 650, "hunt": 651, "hurdle": 652, "husband": 653, "ice": 654, "idea": 655, "image": 656, "improvement": 657, "include": 658, "indium": 659, "information": 660, "ingredient": 661, "inhome": 662, "instal": 663, "instruct": 664, "instruction": 665, "instructor": 666, "instrument": 667, "interact": 668, "interest": 669, "interior": 670, "internet": 671, "interview": 672, "interviewer": 673, "intro": 674, "introduce": 675, "introduction": 676, "involve": 677, "iphone": 678, "iron": 679, "ironman": 680, "island": 681, "item": 682, "jack": 683, "jacket": 684, "jail": 685, "japan": 686, "jar": 687, "jeep": 688, "jimmy": 689, "job": 690, "jockey": 691, "jogger": 692, "john": 693, "joke": 694, "journalist": 695, "judge": 696, "juice": 697, "jump": 698, "jungle": 699, "justin": 700, "keyboard": 701, "kick": 702, "kid": 703, "kill": 704, "king": 705, "kis": 706, "kit": 707, "kitchen": 708, "kitchenthere": 709, "kite": 710, "kitten": 711, "kneel": 712, "knife": 713, "knock": 714, "kombat": 715, "kreuger": 716, "krueger": 717, "kruger": 718, "lab": 719, "laboratory": 720, "lacrosse": 721, "ladle": 722, "lady": 723, "lake": 724, "lamb": 725, "lamborghini": 726, "land": 727, "landscape": 728, "language": 729, "laptop": 730, "laser": 731, "laugh": 732, "launch": 733, "lava": 734, "lavigne": 735, "lawn": 736, "lay": 737, "lead": 738, "leader": 739, "leaf": 740, "lean": 741, "learn": 742, "lecture": 743, "leg": 744, "lego": 745, "lemon": 746, "leonardo": 747, "leopard": 748, "lesson": 749, "letter": 750, "letterman": 751, "level": 752, "library": 753, "lick": 754, "lid": 755, "lie": 756, "life": 757, "lift": 758, "light": 759, "line": 760, "lion": 761, "lipstick": 762, "liquid": 763, "list": 764, "listen": 765, "lizard": 766, "llama": 767, "load": 768, "lobster": 769, "location": 770, "logo": 771, "london": 772, "look": 773, "lot": 774, "lotion": 775, "love": 776, "luigi": 777, "lunch": 778, "macfarlane": 779, "machine": 780, "machinery": 781, "magazine": 782, "magic": 783, "makeup": 784, "male": 785, "mall": 786, "man": 787, "map": 788, "march": 789, "marco": 790, "mario": 791, "market": 792, "marriage": 793, "mascot": 794, "mask": 795, "massage": 796, "mat": 797, "match": 798, "material": 799, "math": 800, "matter": 801, "meal": 802, "meat": 803, "mechanic": 804, "medicine": 805, "meet": 806, "meeting": 807, "melt": 808, "menu": 809, "mermaid": 810, "mes": 811, "message": 812, "metal": 813, "mexico": 814, "michael": 815, "mickey": 816, "microphone": 817, "microwave": 818, "mike": 819, "milk": 820, "minecraft": 821, "mini": 822, "minister": 823, "mirror": 824, "mis": 825, "mix": 826, "mixer": 827, "mixture": 828, "mobile": 829, "mock": 830, "model": 831, "mom": 832, "money": 833, "mongoose": 834, "monitor": 835, "monkey": 836, "monster": 837, "montage": 838, "moon": 839, "morning": 840, "mortal": 841, "mother": 842, "motion": 843, "motor": 844, "motorbike": 845, "motorcycle": 846, "motorcyclist": 847, "mountain": 848, "mouse": 849, "mouth": 850, "move": 851, "movie": 852, "muppet": 853, "murray": 854, "music": 855, "musician": 856, "nail": 857, "name": 858, "narrate": 859, "narrator": 860, "nasa": 861, "nature": 862, "navigate": 863, "neck": 864, "neighborhood": 865, "nestea": 866, "news": 867, "newscast": 868, "newscaster": 869, "newspaper": 870, "night": 871, "ninja": 872, "noise": 873, "norton": 874, "number": 875, "nurse": 876, "obama": 877, "object": 878, "occur": 879, "ocean": 880, "octopu": 881, "office": 882, "officer": 883, "oil": 884, "olympic": 885, "one": 886, "onion": 887, "operate": 888, "opinion": 889, "opponent": 890, "oppose": 891, "orange": 892, "orchestra": 893, "order": 894, "origami": 895, "otehr": 896, "outdoor": 897, "outfit": 898, "oven": 899, "owl": 900, "owner": 901, "pack": 902, "package": 903, "packaging": 904, "paddle": 905, "page": 906, "paint": 907, "painting": 908, "pan": 909, "panda": 910, "panel": 911, "paparazzi": 912, "paper": 913, "parade": 914, "park": 915, "parking": 916, "parody": 917, "parrot": 918, "part": 919, "party": 920, "pas": 921, "passenger": 922, "past": 923, "paste": 924, "pastum": 925, "path": 926, "patient": 927, "patio": 928, "patrick": 929, "patrol": 930, "pay": 931, "peel": 932, "pen": 933, "pencil": 934, "pepper": 935, "perform": 936, "performance": 937, "performer": 938, "person": 939, "pet": 940, "peter": 941, "phil": 942, "phone": 943, "photo": 944, "photograph": 945, "photographer": 946, "photoshop": 947, "piano": 948, "pick": 949, "picture": 950, "pie": 951, "piece": 952, "pig": 953, "pikachu": 954, "pink": 955, "pipe": 956, "pirate": 957, "pistol": 958, "pitch": 959, "pitcher": 960, "pizza": 961, "place": 962, "plan": 963, "plane": 964, "planet": 965, "plant": 966, "plastic": 967, "plate": 968, "platform": 969, "play": 970, "player": 971, "playground": 972, "playing": 973, "pmy": 974, "podium": 975, "point": 976, "pointer": 977, "pokemon": 978, "pole": 979, "polish": 980, "politician": 981, "polouse": 982, "pong": 983, "pony": 984, "pool": 985, "pop": 986, "porch": 987, "pose": 988, "pot": 989, "potato": 990, "powder": 991, "power": 992, "practice": 993, "practise": 994, "pray": 995, "preform": 996, "preparation": 997, "prepare": 998, "pres": 999, "present": 1000, "presentation": 1001, "president": 1002, "pretend": 1003, "preview": 1004, "prey": 1005, "price": 1006, "priest": 1007, "princes": 1008, "prison": 1009, "problem": 1010, "proces": 1011, "product": 1012, "professor": 1013, "program": 1014, "progress": 1015, "project": 1016, "promote": 1017, "protest": 1018, "provide": 1019, "pub": 1020, "pull": 1021, "pump": 1022, "punch": 1023, "puppet": 1024, "puppy": 1025, "purchase": 1026, "purple": 1027, "purse": 1028, "push": 1029, "put": 1030, "puzzle": 1031, "quarterback": 1032, "queen": 1033, "question": 1034, "rabbit": 1035, "race": 1036, "racecar": 1037, "racetrack": 1038, "racing": 1039, "racket": 1040, "radio": 1041, "rail": 1042, "rain": 1043, "raise": 1044, "rally": 1045, "ramp": 1046, "rant": 1047, "rap": 1048, "rapper": 1049, "rat": 1050, "reach": 1051, "react": 1052, "read": 1053, "reader": 1054, "reality": 1055, "receive": 1056, "recipe": 1057, "record": 1058, "referee": 1059, "reflect": 1060, "regard": 1061, "relationship": 1062, "relax": 1063, "repair": 1064, "report": 1065, "reporter": 1066, "research": 1067, "rest": 1068, "restaurant": 1069, "rev": 1070, "reveal": 1071, "review": 1072, "revolve": 1073, "revolver": 1074, "ribbon": 1075, "rice": 1076, "ride": 1077, "rihanna": 1078, "ring": 1079, "rise": 1080, "river": 1081, "road": 1082, "roam": 1083, "roast": 1084, "robert": 1085, "robin": 1086, "robot": 1087, "rock": 1088, "rocket": 1089, "rodent": 1090, "role": 1091, "roll": 1092, "romance": 1093, "roof": 1094, "room": 1095, "rope": 1096, "rotate": 1097, "round": 1098, "routine": 1099, "rub": 1100, "rubik": 1101, "rubix": 1102, "rugby": 1103, "run": 1104, "runner": 1105, "runway": 1106, "rush": 1107, "safety": 1108, "sail": 1109, "salad": 1110, "sale": 1111, "salt": 1112, "sand": 1113, "sandwich": 1114, "santum": 1115, "sauce": 1116, "saw": 1117, "scene": 1118, "scenery": 1119, "school": 1120, "science": 1121, "scientist": 1122, "scoop": 1123, "scooter": 1124, "score": 1125, "scream": 1126, "screen": 1127, "scroll": 1128, "scuba": 1129, "sea": 1130, "search": 1131, "season": 1132, "seat": 1133, "security": 1134, "sedan": 1135, "segment": 1136, "select": 1137, "selfie": 1138, "sell": 1139, "send": 1140, "sequence": 1141, "serve": 1142, "service": 1143, "set": 1144, "sex": 1145, "sexy": 1146, "shadow": 1147, "shake": 1148, "shanium": 1149, "shape": 1150, "share": 1151, "shark": 1152, "shave": 1153, "sheet": 1154, "shelf": 1155, "shift": 1156, "shin": 1157, "ship": 1158, "shirt": 1159, "shirtles": 1160, "shoe": 1161, "shoot": 1162, "shooting": 1163, "shop": 1164, "shopping": 1165, "shore": 1166, "shot": 1167, "shoulder": 1168, "shout": 1169, "show": 1170, "showroom": 1171, "shrimp": 1172, "shuttle": 1173, "side": 1174, "sidewalk": 1175, "sign": 1176, "silver": 1177, "singer": 1178, "singing": 1179, "sink": 1180, "sit": 1181, "site": 1182, "skate": 1183, "skateboard": 1184, "skeleton": 1185, "sketch": 1186, "ski": 1187, "skier": 1188, "skillet": 1189, "skin": 1190, "skirt": 1191, "skit": 1192, "skull": 1193, "skunk": 1194, "sky": 1195, "skydive": 1196, "slam": 1197, "slap": 1198, "sleep": 1199, "slide": 1200, "slideshow": 1201, "slouse": 1202, "smartphone": 1203, "smash": 1204, "smell": 1205, "smile": 1206, "smoke": 1207, "smoking": 1208, "snail": 1209, "snake": 1210, "sniff": 1211, "snow": 1212, "soak": 1213, "soccer": 1214, "society": 1215, "sofa": 1216, "software": 1217, "soldier": 1218, "solve": 1219, "somebody": 1220, "someine": 1221, "someone": 1222, "something": 1223, "son": 1224, "song": 1225, "sort": 1226, "sound": 1227, "soup": 1228, "space": 1229, "spatula": 1230, "speak": 1231, "speaker": 1232, "speaking": 1233, "spec": 1234, "spectacle": 1235, "speech": 1236, "speed": 1237, "spell": 1238, "spend": 1239, "spider": 1240, "spiderman": 1241, "spin": 1242, "spinach": 1243, "splash": 1244, "sponge": 1245, "spongebob": 1246, "spoon": 1247, "sport": 1248, "sportscar": 1249, "spot": 1250, "spray": 1251, "spread": 1252, "square": 1253, "squeeze": 1254, "squid": 1255, "squidward": 1256, "squirrel": 1257, "stab": 1258, "stadium": 1259, "stage": 1260, "stair": 1261, "stand": 1262, "standing": 1263, "star": 1264, "start": 1265, "state": 1266, "station": 1267, "statue": 1268, "steal": 1269, "steam": 1270, "step": 1271, "stephen": 1272, "stick": 1273, "stir": 1274, "stomach": 1275, "store": 1276, "story": 1277, "stove": 1278, "strategy": 1279, "straw": 1280, "stream": 1281, "street": 1282, "stretch": 1283, "strike": 1284, "string": 1285, "stroll": 1286, "stroller": 1287, "structure": 1288, "struggle": 1289, "student": 1290, "studio": 1291, "study": 1292, "stuff": 1293, "stunt": 1294, "style": 1295, "subscribe": 1296, "substance": 1297, "sugar": 1298, "suit": 1299, "sun": 1300, "sunset": 1301, "super": 1302, "superhero": 1303, "superman": 1304, "support": 1305, "surf": 1306, "surface": 1307, "surfboard": 1308, "surfer": 1309, "surgery": 1310, "surprise": 1311, "surround": 1312, "suv": 1313, "swim": 1314, "swimming": 1315, "swing": 1316, "sword": 1317, "symphony": 1318, "sync": 1319, "system": 1320, "table": 1321, "tablet": 1322, "tail": 1323, "talent": 1324, "talk": 1325, "tank": 1326, "tap": 1327, "target": 1328, "taste": 1329, "tattoo": 1330, "tawa": 1331, "taylor": 1332, "tea": 1333, "teach": 1334, "teacher": 1335, "team": 1336, "technique": 1337, "techno": 1338, "technology": 1339, "teen": 1340, "teenage": 1341, "teenager": 1342, "telephone": 1343, "television": 1344, "tell": 1345, "tenni": 1346, "terrain": 1347, "terrorism": 1348, "test": 1349, "text": 1350, "thank": 1351, "theater": 1352, "thing": 1353, "think": 1354, "thor": 1355, "three": 1356, "throw": 1357, "tie": 1358, "tiger": 1359, "time": 1360, "tire": 1361, "toddler": 1362, "toilet": 1363, "tom": 1364, "tomato": 1365, "tool": 1366, "top": 1367, "topic": 1368, "tornado": 1369, "touch": 1370, "touchdown": 1371, "tournament": 1372, "towel": 1373, "tower": 1374, "town": 1375, "toy": 1376, "track": 1377, "tracy": 1378, "traffic": 1379, "trail": 1380, "trailer": 1381, "train": 1382, "training": 1383, "trampoline": 1384, "travel": 1385, "tray": 1386, "treatment": 1387, "tree": 1388, "trek": 1389, "trick": 1390, "trolley": 1391, "trophy": 1392, "trouble": 1393, "truck": 1394, "trump": 1395, "try": 1396, "tshirt": 1397, "tub": 1398, "tube": 1399, "tug": 1400, "tunnel": 1401, "turn": 1402, "turtle": 1403, "tutorial": 1404, "twist": 1405, "two": 1406, "type": 1407, "unbox": 1408, "unison": 1409, "unwrap": 1410, "use": 1411, "van": 1412, "vegetable": 1413, "vehicle": 1414, "vessel": 1415, "victorium": 1416, "victory": 1417, "video": 1418, "videogame": 1419, "view": 1420, "viewer": 1421, "village": 1422, "villain": 1423, "vine": 1424, "violin": 1425, "visit": 1426, "vodka": 1427, "voice": 1428, "voiceover": 1429, "volkswagen": 1430, "volley": 1431, "volleyball": 1432, "vote": 1433, "wait": 1434, "waitres": 1435, "wake": 1436, "walk": 1437, "wall": 1438, "wander": 1439, "want": 1440, "war": 1441, "warehouse": 1442, "wash": 1443, "watch": 1444, "watchmojo": 1445, "water": 1446, "waterfall": 1447, "watermelon": 1448, "wave": 1449, "way": 1450, "weapon": 1451, "wear": 1452, "weather": 1453, "webcam": 1454, "website": 1455, "wed": 1456, "wedding": 1457, "weight": 1458, "whale": 1459, "wheel": 1460, "whisk": 1461, "widow": 1462, "wife": 1463, "wild": 1464, "wildernes": 1465, "win": 1466, "wind": 1467, "window": 1468, "wine": 1469, "winner": 1470, "winter": 1471, "wipe": 1472, "wire": 1473, "witch": 1474, "wok": 1475, "wolf": 1476, "woman": 1477, "wood": 1478, "word": 1479, "work": 1480, "worker": 1481, "workout": 1482, "world": 1483, "wrap": 1484, "wreck": 1485, "wrestle": 1486, "wrestler": 1487, "wrestling": 1488, "write": 1489, "wwe": 1490, "yard": 1491, "yell": 1492, "yoga": 1493, "york": 1494, "youtube": 1495, "zebra": 1496, "zombie": 1497, "zoo": 1498, "zoom": 1499}